myutils/__init__.py
myutils/geo.py
myutils/graph.py
myutils/image.py
myutils/plot.py
myutils/transform.py
myutils/xnet.py
erikunicamp_myutils-0.0.73.dist-info/LICENSE
erikunicamp_myutils-0.0.73.dist-info/METADATA
erikunicamp_myutils-0.0.73.dist-info/WHEEL
erikunicamp_myutils-0.0.73.dist-info/top_level.txt
erikunicamp_myutils-0.0.73.dist-info/RECORD
