Metadata-Version: 2.1
Name: erikunicamp-myutils
Version: 0.0.73
Summary: Utilities package
Home-page: https://github.com/tokudaek/myutils
Author: erikunicamp
Author-email: erik.unicamp@gmail.com
Classifier: Programming Language :: Python :: 3
Classifier: License :: OSI Approved :: MIT License
Classifier: Operating System :: OS Independent
Requires-Python: >=3.6
License-File: LICENSE
